<?xml version="1.0" encoding="UTF-8" standalone="yes"?><ns2:GridDefinitionFileOutputV1 xmlns:ns2="http://www.gtech.com/xml/eInstants/base/common/CatAdminV1"><GridBody><GridProperties><Version>18</Version><GameType>0</GameType><GridSize>1000000</GridSize><RevFileSig>L3IIx6NlCgRvy9vGVDb1Y1v1AL5pUJlQ2xIjGFJitSV5VE58irt6CFKWQour4onYLgFSlnixZmBwCV1HfqQPcA==</RevFileSig><BigEndianFlg>false</BigEndianFlg><SiteID>8</SiteID><PricePoint>500</PricePoint><BetUnits>1</BetUnits><ValidationUnits>1</ValidationUnits><NoOfDivisions>11</NoOfDivisions><LongName>Lucky 7's</LongName><ShortName>LCK7S</ShortName><GridMethod>0</GridMethod><GridTrigger>0</GridTrigger><GridTriggerUnit>0</GridTriggerUnit><VendorID>1</VendorID><IntAuditVendorID>2</IntAuditVendorID><ExtAuditVendorID>0</ExtAuditVendorID><DeliveryChannel>3</DeliveryChannel><Jackpot>false</Jackpot></GridProperties><DivisionRow><Winners>1</Winners><WinAmt>1500000</WinAmt><PrizeTableAmt>1500000</PrizeTableAmt><PrizeType>0</PrizeType></DivisionRow><DivisionRow><Winners>400</Winners><WinAmt>50000</WinAmt><PrizeTableAmt>50000</PrizeTableAmt><PrizeType>0</PrizeType></DivisionRow><DivisionRow><Winners>3900</Winners><WinAmt>17500</WinAmt><PrizeTableAmt>17500</PrizeTableAmt><PrizeType>0</PrizeType></DivisionRow><DivisionRow><Winners>13000</Winners><WinAmt>7500</WinAmt><PrizeTableAmt>7500</PrizeTableAmt><PrizeType>0</PrizeType></DivisionRow><DivisionRow><Winners>8500</Winners><WinAmt>5000</WinAmt><PrizeTableAmt>4000</PrizeTableAmt><PrizeType>0</PrizeType></DivisionRow><DivisionRow><Winners>5500</Winners><WinAmt>4000</WinAmt><PrizeTableAmt>2500</PrizeTableAmt><PrizeType>0</PrizeType></DivisionRow><DivisionRow><Winners>14000</Winners><WinAmt>2500</WinAmt><PrizeTableAmt>1500</PrizeTableAmt><PrizeType>0</PrizeType></DivisionRow><DivisionRow><Winners>10000</Winners><WinAmt>1500</WinAmt><PrizeTableAmt>1000</PrizeTableAmt><PrizeType>0</PrizeType></DivisionRow><DivisionRow><Winners>74528</Winners><WinAmt>1000</WinAmt><PrizeTableAmt>500</PrizeTableAmt><PrizeType>0</PrizeType></DivisionRow><DivisionRow><Winners>97444</Winners><WinAmt>500</WinAmt><PrizeTableAmt>5000</PrizeTableAmt><PrizeType>0</PrizeType></DivisionRow><DivisionRow><Winners>772727</Winners><WinAmt>0</WinAmt><PrizeTableAmt>0</PrizeTableAmt><PrizeType>0</PrizeType></DivisionRow></GridBody><GridFooter><checksum enc="hex">01D0322B0B77C8B2F14B158145C45B3B3153758491B7D4D170275A4D77BD27AC</checksum></GridFooter></ns2:GridDefinitionFileOutputV1>